[{"id":1,"first_name":"Humphrey","last_name":"Orrill","trust":80,"shared_service":"Youtube"},
{"id":2,"first_name":"Cob","last_name":"Timpany","trust":42,"shared_service":"Disney"},
{"id":3,"first_name":"Jean","last_name":"Gomersall","trust":76,"shared_service":"Youtube"},
{"id":4,"first_name":"Bartolomeo","last_name":"Paviour","trust":55,"shared_service":"Youtube"},
{"id":5,"first_name":"Gustaf","last_name":"Hacker","trust":56,"shared_service":"Youtube"},
{"id":6,"first_name":"Miller","last_name":"Rawle","trust":57,"shared_service":"Spotify"},
{"id":7,"first_name":"Nathanael","last_name":"Wolffers","trust":74,"shared_service":"Spotify"},
{"id":8,"first_name":"Etienne","last_name":"Littlecote","trust":76,"shared_service":"HBO"},
{"id":9,"first_name":"Linnet","last_name":"Grisbrook","trust":62,"shared_service":"HBO"},
{"id":10,"first_name":"Tarra","last_name":"Beadell","trust":62,"shared_service":"HBO"},
{"id":11,"first_name":"Isidor","last_name":"Katzmann","trust":49,"shared_service":"HBO"},
{"id":12,"first_name":"Lorrie","last_name":"Giacobelli","trust":85,"shared_service":"HBO"},
{"id":13,"first_name":"Kenneth","last_name":"Sauter","trust":87,"shared_service":"HBO"},
{"id":14,"first_name":"Rina","last_name":"Mollen","trust":48,"shared_service":"Netflix"},
{"id":15,"first_name":"Joline","last_name":"Southerell","trust":83,"shared_service":"Youtube"},
{"id":16,"first_name":"Cynthea","last_name":"Girth","trust":45,"shared_service":"HBO"},
{"id":17,"first_name":"Ernie","last_name":"Aingell","trust":48,"shared_service":"Youtube"},
{"id":18,"first_name":"Loise","last_name":"Fishly","trust":63,"shared_service":"Youtube"},
{"id":19,"first_name":"Kathleen","last_name":"Arndtsen","trust":37,"shared_service":"Youtube"},
{"id":20,"first_name":"Jorry","last_name":"Warlock","trust":93,"shared_service":"HBO"},
{"id":21,"first_name":"Werner","last_name":"Piens","trust":59,"shared_service":"HBO"},
{"id":22,"first_name":"Esta","last_name":"Quixley","trust":86,"shared_service":"Spotify"},
{"id":23,"first_name":"Beniamino","last_name":"Ramelet","trust":55,"shared_service":"HBO"},
{"id":24,"first_name":"Shirley","last_name":"Giacopello","trust":38,"shared_service":"HBO"},
{"id":25,"first_name":"Milena","last_name":"Milborn","trust":80,"shared_service":"HBO"},
{"id":26,"first_name":"Ardine","last_name":"Winear","trust":35,"shared_service":"HBO"},
{"id":27,"first_name":"Frazer","last_name":"Bontein","trust":89,"shared_service":"HBO"},
{"id":28,"first_name":"Corabel","last_name":"Grattage","trust":31,"shared_service":"HBO"},
{"id":29,"first_name":"Inness","last_name":"Glison","trust":72,"shared_service":"HBO"},
{"id":30,"first_name":"Vilhelmina","last_name":"Seelbach","trust":58,"shared_service":"HBO"},
{"id":31,"first_name":"Ariel","last_name":"Costerd","trust":98,"shared_service":"HBO"},
{"id":32,"first_name":"Roxi","last_name":"Earsman","trust":67,"shared_service":"Netflix"},
{"id":33,"first_name":"Luella","last_name":"Tuft","trust":75,"shared_service":"HBO"},
{"id":34,"first_name":"Petunia","last_name":"McClenan","trust":68,"shared_service":"Disney"},
{"id":35,"first_name":"Charlotte","last_name":"Nulty","trust":33,"shared_service":"HBO"},
{"id":36,"first_name":"Pattie","last_name":"Romanini","trust":61,"shared_service":"Netflix"},
{"id":37,"first_name":"Chas","last_name":"Wadly","trust":94,"shared_service":"HBO"},
{"id":38,"first_name":"Wallas","last_name":"Gherardi","trust":61,"shared_service":"Youtube"},
{"id":39,"first_name":"Dorie","last_name":"Haggerty","trust":52,"shared_service":"Disney"},
{"id":40,"first_name":"Sherrie","last_name":"Meekin","trust":71,"shared_service":"HBO"},
{"id":41,"first_name":"Reinold","last_name":"Chrestien","trust":60,"shared_service":"Youtube"},
{"id":42,"first_name":"Travis","last_name":"Benion","trust":93,"shared_service":"Netflix"},
{"id":43,"first_name":"Hayden","last_name":"Concklin","trust":91,"shared_service":"HBO"},
{"id":44,"first_name":"Vasili","last_name":"Carlisle","trust":70,"shared_service":"Youtube"},
{"id":45,"first_name":"Cary","last_name":"Proom","trust":74,"shared_service":"HBO"},
{"id":46,"first_name":"Dona","last_name":"Byrne","trust":66,"shared_service":"Netflix"},
{"id":47,"first_name":"Ileane","last_name":"Le Brom","trust":81,"shared_service":"Spotify"},
{"id":48,"first_name":"Giffy","last_name":"Steventon","trust":82,"shared_service":"Spotify"},
{"id":49,"first_name":"Margie","last_name":"Scallan","trust":77,"shared_service":"HBO"},
{"id":50,"first_name":"Sher","last_name":"Wissbey","trust":62,"shared_service":"Youtube"},
{"id":51,"first_name":"Analiese","last_name":"Ferreiro","trust":38,"shared_service":"Youtube"},
{"id":52,"first_name":"Sayers","last_name":"Walby","trust":34,"shared_service":"HBO"},
{"id":53,"first_name":"Timmy","last_name":"McLurg","trust":48,"shared_service":"Youtube"},
{"id":54,"first_name":"Freeland","last_name":"Fendley","trust":35,"shared_service":"HBO"},
{"id":55,"first_name":"Kathie","last_name":"Humm","trust":66,"shared_service":"Disney"},
{"id":56,"first_name":"Damaris","last_name":"Evitt","trust":65,"shared_service":"Youtube"},
{"id":57,"first_name":"Laurens","last_name":"Cadden","trust":64,"shared_service":"HBO"},
{"id":58,"first_name":"Mab","last_name":"Hubbins","trust":71,"shared_service":"HBO"},
{"id":59,"first_name":"Jodi","last_name":"Harbard","trust":54,"shared_service":"HBO"},
{"id":60,"first_name":"Man","last_name":"Barette","trust":66,"shared_service":"HBO"},
{"id":61,"first_name":"Kaylyn","last_name":"Stening","trust":41,"shared_service":"Spotify"},
{"id":62,"first_name":"Hillary","last_name":"Rodie","trust":58,"shared_service":"Netflix"},
{"id":63,"first_name":"Uriel","last_name":"Timlett","trust":56,"shared_service":"HBO"},
{"id":64,"first_name":"Farlee","last_name":"Jellico","trust":97,"shared_service":"Youtube"},
{"id":65,"first_name":"Rikki","last_name":"Brookhouse","trust":86,"shared_service":"HBO"},
{"id":66,"first_name":"Arv","last_name":"Gianninotti","trust":44,"shared_service":"Youtube"},
{"id":67,"first_name":"Roxy","last_name":"Sailes","trust":71,"shared_service":"HBO"},
{"id":68,"first_name":"Budd","last_name":"Moverley","trust":97,"shared_service":"HBO"},
{"id":69,"first_name":"Paulie","last_name":"Joly","trust":88,"shared_service":"HBO"},
{"id":70,"first_name":"Herc","last_name":"Corday","trust":70,"shared_service":"HBO"},
{"id":71,"first_name":"Boris","last_name":"Heart","trust":62,"shared_service":"HBO"},
{"id":72,"first_name":"Vivyanne","last_name":"Brims","trust":56,"shared_service":"Youtube"},
{"id":73,"first_name":"Sophi","last_name":"Choke","trust":100,"shared_service":"Youtube"},
{"id":74,"first_name":"Jenni","last_name":"Greser","trust":87,"shared_service":"HBO"},
{"id":75,"first_name":"Ardath","last_name":"Streeten","trust":59,"shared_service":"Youtube"},
{"id":76,"first_name":"Chrissy","last_name":"Delamaine","trust":34,"shared_service":"HBO"},
{"id":77,"first_name":"Cyndie","last_name":"Heinert","trust":64,"shared_service":"HBO"},
{"id":78,"first_name":"Marthe","last_name":"Gohier","trust":75,"shared_service":"Youtube"},
{"id":79,"first_name":"Betsy","last_name":"Sullly","trust":88,"shared_service":"HBO"},
{"id":80,"first_name":"Avrit","last_name":"Hansana","trust":52,"shared_service":"Disney"},
{"id":81,"first_name":"Rip","last_name":"Bagworth","trust":52,"shared_service":"HBO"},
{"id":82,"first_name":"Loni","last_name":"Brandenberg","trust":72,"shared_service":"Spotify"},
{"id":83,"first_name":"Jarrid","last_name":"Fee","trust":47,"shared_service":"HBO"},
{"id":84,"first_name":"Manolo","last_name":"Farres","trust":38,"shared_service":"HBO"},
{"id":85,"first_name":"Calla","last_name":"Brockett","trust":100,"shared_service":"HBO"},
{"id":86,"first_name":"Latrina","last_name":"Ambrosi","trust":65,"shared_service":"Netflix"},
{"id":87,"first_name":"Helen-elizabeth","last_name":"Dorsey","trust":36,"shared_service":"HBO"},
{"id":88,"first_name":"Edgardo","last_name":"Tissier","trust":64,"shared_service":"HBO"},
{"id":89,"first_name":"Alika","last_name":"Cescot","trust":49,"shared_service":"HBO"},
{"id":90,"first_name":"Frannie","last_name":"Gietz","trust":86,"shared_service":"HBO"},
{"id":91,"first_name":"Maurita","last_name":"Fusedale","trust":99,"shared_service":"Youtube"},
{"id":92,"first_name":"Jess","last_name":"De Giorgio","trust":33,"shared_service":"HBO"},
{"id":93,"first_name":"Marilyn","last_name":"Featherston","trust":99,"shared_service":"Youtube"},
{"id":94,"first_name":"Johanna","last_name":"Bimrose","trust":93,"shared_service":"HBO"},
{"id":95,"first_name":"Nancy","last_name":"Flieg","trust":37,"shared_service":"HBO"},
{"id":96,"first_name":"Chancey","last_name":"Bartle","trust":77,"shared_service":"HBO"},
{"id":97,"first_name":"Cherice","last_name":"MacDermid","trust":70,"shared_service":"Youtube"},
{"id":98,"first_name":"Joella","last_name":"Hark","trust":58,"shared_service":"HBO"},
{"id":99,"first_name":"Alison","last_name":"Wormleighton","trust":55,"shared_service":"HBO"},
{"id":100,"first_name":"Ginni","last_name":"Fernez","trust":50,"shared_service":"Youtube"}]